{
  "generated_at": "2026-04-24T08:08:50",
  "outputs": [
    "data\\processed\\secciones_leon_bivariate.geojson",
    "data\\processed\\editorial-map-spec.json",
    "public\\data\\secciones.geojson",
    "public\\config\\editorial-map-spec.json",
    "reports\\data_qa\\web_bundle_report.md",
    "reports\\data_qa\\web_bundle_report.json"
  ],
  "counts": {
    "features": 846,
    "class_counts": {
      "decline_low": 3,
      "decline_mid": 1,
      "decline_high": 0,
      "stable_low": 7,
      "stable_mid": 428,
      "stable_high": 122,
      "growth_low": 0,
      "growth_mid": 30,
      "growth_high": 106,
      "no_data": 149
    },
    "no_data_count": 149,
    "has_data_false_count": 149
  },
  "payload": {
    "bytes": 2729600,
    "mb": 2.603,
    "public_data_geojson_bytes": 2725385,
    "public_spec_json_bytes": 4215
  },
  "contract_validation": {
    "required_fields_present": true,
    "unexpected_fields_present": [],
    "missing_fields": [],
    "ordered_fields_match": true
  },
  "qa_validations": {
    "public_data_exists": true,
    "public_config_exists": true,
    "feature_count": 846,
    "feature_count_expected_846": true,
    "duplicate_section_ids": 0,
    "all_classes_in_domain": true,
    "class_counts_match_epic_2_3": true,
    "no_data_count": 149,
    "no_data_expected_149": true,
    "has_data_false_count": 149,
    "has_data_false_expected_149": true,
    "has_data_no_data_inconsistency": 0,
    "all_colors_present": true,
    "all_colors_in_class_map": true,
    "contract_required_fields": true,
    "contract_no_missing_fields": true,
    "contract_no_unexpected_fields": true,
    "frontend_files_in_public": [],
    "no_data_matches_epic_2_3_report": true,
    "has_data_false_matches_epic_2_3_report": true
  },
  "warnings": [
    "is_in_inset se asigno en false por defecto; no existe geometria formal de inset en esta fase.",
    "CRS indicaba EPSG:4326 pero coordenadas no estaban en rango geodesico; se corrigio asumiendo EPSG:32614."
  ],
  "pending_frontend": [
    "Definir geometria y posicion final de inset urbano (is_in_inset).",
    "Implementar render MapLibre y microinteracciones editoriales.",
    "Aplicar jerarquia tipografica final y composicion visual de la leyenda 3x3."
  ],
  "spec_summary": {
    "project_id": "leon_pan_bivariate",
    "title": "Comportamiento del voto panista en Leon",
    "subtitle": "Variacion del voto PAN entre 2018 y 2021 por seccion electoral",
    "interaction_policy": "replica fiel + microinteracciones",
    "data_files": {
      "secciones": "/data/secciones.geojson"
    }
  },
  "decision": "aprobado para Epica 3"
}